earthspeed/__init__.py
earthspeed/windfinder.py
earthspeed-1.2.dist-info/LICENSE
earthspeed-1.2.dist-info/METADATA
earthspeed-1.2.dist-info/WHEEL
earthspeed-1.2.dist-info/top_level.txt
earthspeed-1.2.dist-info/RECORD
