Metadata-Version: 2.1
Name: earthspeed
Version: 1.2
Summary: Finding the Earth velocity relative to the dark matter halo
Author-email: "Ben G. Lillard" <blillard@uoregon.edu>
Project-URL: Homepage, https://github.com/blillard/earthspeed
Project-URL: Source, https://github.com/blillard/earthspeed/
Project-URL: Documentation, https://github.com/blillard/earthspeed/blob/main/README.md
Classifier: Intended Audience :: Science/Research
Classifier: Topic :: Scientific/Engineering :: Physics
Classifier: Programming Language :: Python :: 3
Requires-Python: >=3.7
License-File: LICENSE
Requires-Dist: astropy
